agent_flows/__init__.py
agent_flows/exceptions.py
agent_flows/api/__init__.py
agent_flows/api/error_mapping.py
agent_flows/api/http_client.py
agent_flows/core/__init__.py
agent_flows/core/execution/__init__.py
agent_flows/core/execution/executor.py
agent_flows/core/execution/registry.py
agent_flows/core/execution/runner.py
agent_flows/core/execution/state.py
agent_flows/core/execution/step_executor.py
agent_flows/core/flows/__init__.py
agent_flows/core/flows/cache.py
agent_flows/core/flows/loader.py
agent_flows/core/flows/registry.py
agent_flows/core/resources/__init__.py
agent_flows/core/resources/credentials.py
agent_flows/core/resources/interpolation.py
agent_flows/core/resources/mcp_sessions.py
agent_flows/core/resources/variables.py
agent_flows/executors/__init__.py
agent_flows/executors/api_call.py
agent_flows/executors/base.py
agent_flows/executors/code_interpreter.py
agent_flows/executors/conditional.py
agent_flows/executors/finish.py
agent_flows/executors/flow_variables.py
agent_flows/executors/llm_instruction.py
agent_flows/executors/loop.py
agent_flows/executors/mcp_server_action.py
agent_flows/executors/run_command.py
agent_flows/executors/set_variables.py
agent_flows/executors/stream_ui.py
agent_flows/executors/switch.py
agent_flows/executors/web_scraping.py
agent_flows/executors/web_search.py
agent_flows/integrations/__init__.py
agent_flows/integrations/llm_providers.py
agent_flows/integrations/mcp_client.py
agent_flows/models/__init__.py
agent_flows/models/config.py
agent_flows/models/credentials.py
agent_flows/models/execution.py
agent_flows/models/flow.py
agent_flows/models/test.py
agent_flows/models/executors/__init__.py
agent_flows/models/executors/api_call.py
agent_flows/models/executors/code_interpreter.py
agent_flows/models/executors/conditional.py
agent_flows/models/executors/finish.py
agent_flows/models/executors/flow_variables.py
agent_flows/models/executors/llm_instruction.py
agent_flows/models/executors/loop.py
realtimex_agent_flows-0.8.0.dist-info/METADATA
realtimex_agent_flows-0.8.0.dist-info/WHEEL
realtimex_agent_flows-0.8.0.dist-info/RECORD
