Metadata-Version: 2.4
Name: realtimex-agent-flows
Version: 0.8.0
Summary: Python library for executing Agent Flows - visual, no-code workflows for AI agents
Author-email: RealTimeX Team <info@realtimex.ai>
Keywords: agents,ai,automation,llm,workflows
Requires-Python: >=3.11
Requires-Dist: aiofiles>=23.2.0
Requires-Dist: aiohttp>=3.9.0
Requires-Dist: cryptography==44.0.3
Requires-Dist: jmespath>=1.0.1
Requires-Dist: jsonpath-ng>=1.6.0
Requires-Dist: litellm>=1.76.3
Requires-Dist: mcp>=1.0.0
Requires-Dist: pydantic>=2.5.0
Requires-Dist: python-dateutil>=2.9.0.post0
Requires-Dist: python-dotenv>=1.1.1
Requires-Dist: pyyaml>=6.0.0
Requires-Dist: realtimex-web-scraping-mcp-server
Requires-Dist: realtimex-web-search-mcp-server
Requires-Dist: redis>=6.4.0
Requires-Dist: simpleeval>=1.0.3
Requires-Dist: structlog>=23.2.0
Requires-Dist: tenacity>=8.2.0
Requires-Dist: typing-extensions>=4.8.0
